dojo/__init__.py
dojo/cli.py
dojo/main.py
dojoupload-0.1.dist-info/METADATA
dojoupload-0.1.dist-info/WHEEL
dojoupload-0.1.dist-info/top_level.txt
dojoupload-0.1.dist-info/RECORD
